{
    "link": "http://zh.moegirl.org/CANAAN",
    "name": "CANAAN",
    "firstp": [
        "428 ～被封锁的涉谷～",
        "魔都",
        "TYPE-MOON",
        "P.A.WORKS"
    ],
    "photo": "//static.mengniang.org/thumb/0/04/Canaan-1.jpg/250px-Canaan-1.jpg",
    "作品原名": " CANNAN ",
    "作品译名": " 迦南 ",
    "原作载体": " 动画 ",
    "原作作者": " CHUNSOFT/TYPE-MOON ",
    "改编载体": " 小说、漫画 ",
    "相关作品": "428 ～被封锁的涉谷～",
    "catlinks": [
        "日本动画作品",
        "CANAAN",
        "超能力题材",
        "黑道题材",
        "悬疑推理题材"
    ]
}