{
    "link": "http://zh.moegirl.org/%E6%8A%98%E5%8E%9F%E7%94%98%E4%B9%90",
    "name": "折原甘乐",
    "firstp": [
        "成田良悟",
        "无头骑士异闻录"
    ],
    "本名": " 折原临也 ",
    "别号": " 临娘、甘乐酱 ",
    "生日": "5月4日",
    "年龄": " 20代前半 ",
    "身高": " 169cm ",
    "体重": " 55kg ",
    "瞳色": "红瞳",
    "发色": "黑发",
    "声优": "神谷浩史",
    "萌点": " 腹黑 ",
    "catlinks": [
        "人物",
        "折原甘乐",
        "无设定图",
        "5月4日",
        "红瞳",
        "黑发",
        "神谷浩史"
    ]
} "黑发",
        "神谷浩史"
    ]
}