{
    "link": "http://zh.moegirl.org/%E7%88%B1%E5%A8%9C%C2%B7%E9%9C%8D%E9%A1%BF",
    "name": "爱娜·霍顿",
    "firstp": [
        "Falcom",
        "英雄传说 轨迹系列"
    ],
    "本名": " 爱娜·霍顿 ",
    "瞳色": "紫罗兰瞳",
    "发色": "金发",
    "声优": "鹿野优以",
    "萌点": "看板娘",
    "出身地区": " 利贝尔王国 ",
    "主要活动范围": " 利贝尔王国洛连特市 ",
    "所属团体": "游击士协会",
    "个人状态": " 虽说是拼酒，其实也就是陪他们玩玩而已呢。 ",
    "catlinks": [
        "人物",
        "爱娜·霍顿",
        "无设定图",
        "紫罗兰瞳",
        "金发",
        "鹿野优以",
        "轨迹系列",
        "看板娘",
        "大小姐"
    ]
}