{
    "link": "http://zh.moegirl.org/%E7%BC%87%E5%8D%93",
    "name": "缇卓",
    "firstp": [
        "刀剑神域"
    ],
    "photo": "//static.mengniang.org/2/27/%E7%BC%87%E5%8D%931.png",
    "本名": " 缇卓·施特莉涅恩 ",
    "别号": " 缇卓/蒂洁 ",
    "年龄": " 16岁 ",
    "瞳色": "红瞳",
    "发色": "红发",
    "萌点": " 红发 ",
    "出身地区": " Under World ",
    "主要活动范围": " Under World ",
    "所属团体": " 北圣托利亚帝立修剑学院 ",
    "catlinks": [
        "人物",
        "缇卓",
        "红瞳",
        "红发",
        "刀剑神域"
    ]
}",
    "catlinks": [
        "人物",
        "缇卓",
        "红瞳",
        "红发",
        "刀剑神域"
    ]
}