{
    "link": "http://zh.moegirl.org/%E7%BC%87%E6%AC%A7%C2%B7%E6%99%AE%E6%8B%89%E6%89%98",
    "name": "缇欧·普拉托",
    "firstp": [
        "《英雄传说：零之轨迹》",
        "《英雄传说：碧之轨迹》"
    ],
    "photo": "//static.mengniang.org/thumb/e/e9/Tio-Plato.jpg/250px-Tio-Plato.jpg",
    "本名": " 缇欧•普拉托(ティオ•プラトー)(Tio Plato) ",
    "别号": " 猫萝 喵萝 阿缇 ",
    "瞳色": "金瞳",
    "发色": "青发",
    "萌点": "毒舌",
    "出身地区": "雷米菲利亚公国",
    "主要活动范围": " 克洛斯贝尔而自治州及周边地区 ",
    "所属团体": " 克洛斯贝尔警察局所属特别任务支援科（SSS）<s>克洛斯贝尔城管大队</s>   普斯泰恩财团魔导杖小组外派测试人员 ",
    "catlinks": [
        "人物",
        "缇欧·普拉托",
        "金瞳",
        "青发",
        "轨迹系列"
    ]
}